rastervision/pytorch_backend/__init__.py
rastervision/pytorch_backend/py.typed
rastervision/pytorch_backend/pytorch_chip_classification.py
rastervision/pytorch_backend/pytorch_chip_classification_config.py
rastervision/pytorch_backend/pytorch_learner_backend.py
rastervision/pytorch_backend/pytorch_learner_backend_config.py
rastervision/pytorch_backend/pytorch_object_detection.py
rastervision/pytorch_backend/pytorch_object_detection_config.py
rastervision/pytorch_backend/pytorch_semantic_segmentation.py
rastervision/pytorch_backend/pytorch_semantic_segmentation_config.py
rastervision/pytorch_backend/utils.py
rastervision/pytorch_backend/examples/__init__.py
rastervision/pytorch_backend/examples/test.py
rastervision/pytorch_backend/examples/tiny_spacenet.py
rastervision/pytorch_backend/examples/utils.py
rastervision/pytorch_backend/examples/chip_classification/__init__.py
rastervision/pytorch_backend/examples/chip_classification/spacenet_rio.py
rastervision/pytorch_backend/examples/object_detection/__init__.py
rastervision/pytorch_backend/examples/object_detection/cowc_potsdam.py
rastervision/pytorch_backend/examples/object_detection/xview.py
rastervision/pytorch_backend/examples/object_detection/cowc_potsdam_data_prep/__init__.py
rastervision/pytorch_backend/examples/object_detection/cowc_potsdam_data_prep/merge_geojson.py
rastervision/pytorch_backend/examples/object_detection/cowc_potsdam_data_prep/prepare_potsdam.py
rastervision/pytorch_backend/examples/object_detection/cowc_potsdam_data_prep/resample_geotiffs.py
rastervision/pytorch_backend/examples/object_detection/cowc_potsdam_data_prep/transfer_georeference.py
rastervision/pytorch_backend/examples/semantic_segmentation/__init__.py
rastervision/pytorch_backend/examples/semantic_segmentation/isprs_potsdam.py
rastervision/pytorch_backend/examples/semantic_segmentation/isprs_potsdam_multi_source.py
rastervision/pytorch_backend/examples/semantic_segmentation/spacenet_vegas.py
rastervision_pytorch_backend-0.31.1.dist-info/METADATA
rastervision_pytorch_backend-0.31.1.dist-info/WHEEL
rastervision_pytorch_backend-0.31.1.dist-info/top_level.txt
rastervision_pytorch_backend-0.31.1.dist-info/RECORD
